Challenge07_StopTimer/stop_timer.v
module stop_timer(
    input clk,
    input reset,
    input start,
    input stop,
    output reg [7:0] time_count
);

parameter IDLE = 1'b0;
parameter RUN  = 1'b1;

reg state;

always @(posedge clk or posedge reset)
begin
    if(reset)
    begin
        state <= IDLE;
        time_count <= 8'd0;
    end
    else
    begin
        case(state)

        IDLE:
        begin
            if(start)
                state <= RUN;
        end

        RUN:
        begin
            if(stop)
                state <= IDLE;
            else
                time_count <= time_count + 1;
        end

        endcase
    end
end

endmodule

Challenge07_StopTimer/stop_timer_tb.v
`timescale 1ns/1ps

module stop_timer_tb;

reg clk;
reg reset;
reg start;
reg stop;

wire [7:0] time_count;

stop_timer uut(
    .clk(clk),
    .reset(reset),
    .start(start),
    .stop(stop),
    .time_count(time_count)
);

// Clock generation
always #5 clk = ~clk;

initial
begin

    $dumpfile("stop_timer.vcd");
    $dumpvars(0, stop_timer_tb);

    $monitor("Time=%0t Reset=%b Start=%b Stop=%b Count=%d",
             $time, reset, start, stop, time_count);

    clk = 0;
    reset = 1;
    start = 0;
    stop = 0;

    // Reset
    #10;
    reset = 0;

    // Start stopwatch
    #10;
    start = 1;
    #10;
    start = 0;

    // Run for 5 clock cycles
    #50;

    // Stop stopwatch
    stop = 1;
    #10;
    stop = 0;

    // Wait
    #30;

    // Start again
    start = 1;
    #10;
    start = 0;

    // Run for 3 clock cycles
    #30;

    // Reset
    reset = 1;
    #10;
    reset = 0;

    #20;

    $finish;

end

endmodule

Challenge07_StopTimer/stop_timer.vcd
$date
	Sun Jul 12 20:37:29 2026
$end
$version
	Icarus Verilog
$end
$timescale
	1ps
$end
$scope module stop_timer_tb $end
$var wire 8 ! time_count [7:0] $end
$var reg 1 " clk $end
$var reg 1 # reset $end
$var reg 1 $ start $end
$var reg 1 % stop $end
$scope module uut $end
$var wire 1 " clk $end
$var wire 1 # reset $end
$var wire 1 $ start $end
$var wire 1 % stop $end
$var parameter 1 & IDLE $end
$var parameter 1 ' RUN $end
$var reg 1 ( state $end
$var reg 8 ) time_count [7:0] $end
$upscope $end
$upscope $end
$enddefinitions $end
$comment Show the parameter values. $end
$dumpall
1'
0&
$end
#0
$dumpvars
b0 )
0(
0%
0$
1#
0"
b0 !
$end
#5000
1"
#10000
0"
0#
#15000
1"
#20000
0"
1$
#25000
1(
1"
#30000
0"
0$
#35000
b1 !
b1 )
1"
#40000
0"
#45000
b10 !
b10 )
1"
#50000
0"
#55000
b11 !
b11 )
1"
#60000
0"
#65000
b100 !
b100 )
1"
#70000
0"
#75000
b101 !
b101 )
1"
#80000
0"
1%
#85000
0(
1"
#90000
0"
0%
#95000
1"
#100000
0"
#105000
1"
#110000
0"
#115000
1"
#120000
0"
1$
#125000
1(
1"
#130000
0"
0$
#135000
b110 !
b110 )
1"
#140000
0"
#145000
b111 !
b111 )
1"
#150000
0"
#155000
b1000 !
b1000 )
1"
#160000
b0 !
b0 )
0(
0"
1#
#165000
1"
#170000
0"
0#
