Challenge04_PriorityLock/priority_lock.v
module priority_lock(
    input clk,
    input reset,
    input [3:0] req,
    output reg [3:0] grant
);

reg [1:0] pointer;

always @(posedge clk or posedge reset)
begin
    if(reset)
    begin
        pointer <= 2'd0;
        grant <= 4'b0000;
    end
    else
    begin
        grant <= 4'b0000;

        case(pointer)

        2'd0:
        begin
            if(req[0]) begin grant<=4'b0001; pointer<=2'd1; end
            else if(req[1]) begin grant<=4'b0010; pointer<=2'd2; end
            else if(req[2]) begin grant<=4'b0100; pointer<=2'd3; end
            else if(req[3]) begin grant<=4'b1000; pointer<=2'd0; end
        end

        2'd1:
        begin
            if(req[1]) begin grant<=4'b0010; pointer<=2'd2; end
            else if(req[2]) begin grant<=4'b0100; pointer<=2'd3; end
            else if(req[3]) begin grant<=4'b1000; pointer<=2'd0; end
            else if(req[0]) begin grant<=4'b0001; pointer<=2'd1; end
        end

        2'd2:
        begin
            if(req[2]) begin grant<=4'b0100; pointer<=2'd3; end
            else if(req[3]) begin grant<=4'b1000; pointer<=2'd0; end
            else if(req[0]) begin grant<=4'b0001; pointer<=2'd1; end
            else if(req[1]) begin grant<=4'b0010; pointer<=2'd2; end
        end

        2'd3:
        begin
            if(req[3]) begin grant<=4'b1000; pointer<=2'd0; end
            else if(req[0]) begin grant<=4'b0001; pointer<=2'd1; end
            else if(req[1]) begin grant<=4'b0010; pointer<=2'd2; end
            else if(req[2]) begin grant<=4'b0100; pointer<=2'd3; end
        end

        endcase
    end
end

endmodule

Challenge04_PriorityLock/priority_lock_tb.v
`timescale 1ns/1ps

module priority_lock_tb;

reg clk;
reg reset;
reg [3:0] req;

wire [3:0] grant;

priority_lock uut(
    .clk(clk),
    .reset(reset),
    .req(req),
    .grant(grant)
);

always #5 clk = ~clk;

initial
begin

    $dumpfile("priority_lock.vcd");
    $dumpvars(0,priority_lock_tb);

    $monitor("Time=%0t Req=%b Grant=%b",
              $time,req,grant);

    clk=0;
    reset=1;
    req=4'b0000;

    #10;
    reset=0;

    // Single request
    #10 req=4'b0001;

    // Multiple requests
    #20 req=4'b1110;

    // Persistent requests
    #40 req=4'b1111;

    // Request changes
    #40 req=4'b0101;

    // No request
    #30 req=4'b0000;

    #20;

    $finish;

end

endmodule

Challenge04_PriorityLock/priority_lock.vcd
$date
	Sun Jul 12 20:10:41 2026
$end
$version
	Icarus Verilog
$end
$timescale
	1ps
$end
$scope module priority_lock_tb $end
$var wire 4 ! grant [3:0] $end
$var reg 1 " clk $end
$var reg 4 # req [3:0] $end
$var reg 1 $ reset $end
$scope module uut $end
$var wire 1 " clk $end
$var wire 4 % req [3:0] $end
$var wire 1 $ reset $end
$var reg 4 & grant [3:0] $end
$var reg 2 ' pointer [1:0] $end
$upscope $end
$upscope $end
$enddefinitions $end
$comment Show the parameter values. $end
$dumpall
$end
#0
$dumpvars
b0 '
b0 &
b0 %
1$
b0 #
0"
b0 !
$end
#5000
1"
#10000
0"
0$
#15000
1"
#20000
0"
b1 #
b1 %
#25000
b1 '
b1 !
b1 &
1"
#30000
0"
#35000
b1 !
b1 &
1"
#40000
0"
b1110 #
b1110 %
#45000
b10 '
b10 !
b10 &
1"
#50000
0"
#55000
b11 '
b100 !
b100 &
1"
#60000
0"
#65000
b0 '
b1000 !
b1000 &
1"
#70000
0"
#75000
b10 '
b10 !
b10 &
1"
#80000
0"
b1111 #
b1111 %
#85000
b11 '
b100 !
b100 &
1"
#90000
0"
#95000
b0 '
b1000 !
b1000 &
1"
#100000
0"
#105000
b1 '
b1 !
b1 &
1"
#110000
0"
#115000
b10 '
b10 !
b10 &
1"
#120000
0"
b101 #
b101 %
#125000
b11 '
b100 !
b100 &
1"
#130000
0"
#135000
b1 '
b1 !
b1 &
1"
#140000
0"
#145000
b11 '
b100 !
b100 &
1"
#150000
0"
b0 #
b0 %
#155000
b0 !
b0 &
1"
