Challeng06_RingBuffer/ring_buffer.v
module ring_buffer(
    input clk,
    input reset,
    input write_en,
    input read_en,
    input [7:0] data_in,
    output reg [7:0] data_out,
    output full,
    output empty
);

reg [7:0] fifo[0:3];

reg [1:0] write_ptr;
reg [1:0] read_ptr;
reg [2:0] count;

assign full = (count == 4);
assign empty = (count == 0);

always @(posedge clk or posedge reset)
begin
    if(reset)
    begin
        write_ptr <= 0;
        read_ptr <= 0;
        count <= 0;
        data_out <= 0;
    end
    else
    begin
        // Write
        if(write_en && !full)
        begin
            fifo[write_ptr] <= data_in;
            write_ptr <= write_ptr + 1;
            count <= count + 1;
        end

        // Read
        if(read_en && !empty)
        begin
            data_out <= fifo[read_ptr];
            read_ptr <= read_ptr + 1;
            count <= count - 1;
        end
    end
end

endmodule

Challeng06_RingBuffer/ring_buffer_tb.v
`timescale 1ns/1ps

module ring_buffer_tb;

reg clk;
reg reset;
reg write_en;
reg read_en;
reg [7:0] data_in;

wire [7:0] data_out;
wire full;
wire empty;

ring_buffer uut(
    .clk(clk),
    .reset(reset),
    .write_en(write_en),
    .read_en(read_en),
    .data_in(data_in),
    .data_out(data_out),
    .full(full),
    .empty(empty)
);

// Clock
always #5 clk = ~clk;

initial
begin

    $dumpfile("ring_buffer.vcd");
    $dumpvars(0, ring_buffer_tb);

    $monitor("Time=%0t WE=%b RE=%b DataIn=%d DataOut=%d Full=%b Empty=%b",
             $time, write_en, read_en, data_in, data_out, full, empty);

    clk = 0;
    reset = 1;
    write_en = 0;
    read_en = 0;
    data_in = 0;

    #10;
    reset = 0;

    // Write 10
    write_en = 1;
    data_in = 10;
    #10;

    // Write 20
    data_in = 20;
    #10;

    // Write 30
    data_in = 30;
    #10;

    // Write 40
    data_in = 40;
    #10;

    write_en = 0;

    // Read 10
    read_en = 1;
    #10;

    // Read 20
    #10;

    // Read 30
    #10;

    // Read 40
    #10;

    read_en = 0;

    // Wrap-around test
    write_en = 1;
    data_in = 55;
    #10;

    data_in = 66;
    #10;

    write_en = 0;

    read_en = 1;
    #20;

    read_en = 0;

    #20;

    $finish;

end

endmodule

Challeng06_RingBuffer/ring_buffer.vcd
$date
	Sun Jul 12 20:33:33 2026
$end
$version
	Icarus Verilog
$end
$timescale
	1ps
$end
$scope module ring_buffer_tb $end
$var wire 1 ! full $end
$var wire 1 " empty $end
$var wire 8 # data_out [7:0] $end
$var reg 1 $ clk $end
$var reg 8 % data_in [7:0] $end
$var reg 1 & read_en $end
$var reg 1 ' reset $end
$var reg 1 ( write_en $end
$scope module uut $end
$var wire 1 $ clk $end
$var wire 8 ) data_in [7:0] $end
$var wire 1 & read_en $end
$var wire 1 ' reset $end
$var wire 1 ( write_en $end
$var wire 1 ! full $end
$var wire 1 " empty $end
$var reg 3 * count [2:0] $end
$var reg 8 + data_out [7:0] $end
$var reg 2 , read_ptr [1:0] $end
$var reg 2 - write_ptr [1:0] $end
$upscope $end
$upscope $end
$enddefinitions $end
$comment Show the parameter values. $end
$dumpall
$end
#0
$dumpvars
b0 -
b0 ,
b0 +
b0 *
b0 )
0(
1'
0&
b0 %
0$
b0 #
1"
0!
$end
#5000
1$
#10000
0$
b1010 %
b1010 )
1(
0'
#15000
0"
b1 *
b1 -
1$
#20000
0$
b10100 %
b10100 )
#25000
b10 *
b10 -
1$
#30000
0$
b11110 %
b11110 )
#35000
b11 *
b11 -
1$
#40000
0$
b101000 %
b101000 )
#45000
1!
b100 *
b0 -
1$
#50000
0$
1&
0(
#55000
0!
b11 *
b1 ,
b1010 #
b1010 +
1$
#60000
0$
#65000
b10 *
b10 ,
b10100 #
b10100 +
1$
#70000
0$
#75000
b1 *
b11 ,
b11110 #
b11110 +
1$
#80000
0$
#85000
1"
b0 *
b0 ,
b101000 #
b101000 +
1$
#90000
0$
b110111 %
b110111 )
1(
0&
#95000
0"
b1 *
b1 -
1$
#100000
0$
b1000010 %
b1000010 )
#105000
b10 *
b10 -
1$
#110000
0$
1&
0(
#115000
b1 *
b1 ,
b110111 #
b110111 +
1$
#120000
0$
#125000
1"
b0 *
b10 ,
b1000010 #
b1000010 +
1$
#130000
0$
0&
