Challenge10_ModeMux/mode_mux.v
module mode_mux(
    input clk,
    input reset,
    input [3:0] req,
    input mode,              // 0 = Fixed Priority, 1 = Round Robin

    output reg [1:0] grant,
    output reg valid
);

reg [1:0] pointer;


// Round Robin priority pointer
always @(posedge clk or posedge reset)
begin

    if(reset)
    begin
        pointer <= 2'b00;
        grant <= 2'b00;
        valid <= 1'b0;
    end

    else
    begin

        valid <= 1'b0;


        // ---------------------------
        // Fixed Priority Mode
        // Priority: req3 > req2 > req1 > req0
        // ---------------------------

        if(mode == 1'b0)
        begin

            if(req[3])
            begin
                grant <= 2'b11;
                valid <= 1'b1;
            end

            else if(req[2])
            begin
                grant <= 2'b10;
                valid <= 1'b1;
            end

            else if(req[1])
            begin
                grant <= 2'b01;
                valid <= 1'b1;
            end

            else if(req[0])
            begin
                grant <= 2'b00;
                valid <= 1'b1;
            end

        end



        // ---------------------------
        // Round Robin Mode
        // ---------------------------

        else
        begin

            case(pointer)

            2'b00:
            begin
                if(req[0])
                begin
                    grant <= 2'b00;
                    pointer <= 2'b01;
                    valid <= 1'b1;
                end
                else if(req[1])
                begin
                    grant <= 2'b01;
                    pointer <= 2'b10;
                    valid <= 1'b1;
                end
                else if(req[2])
                begin
                    grant <= 2'b10;
                    pointer <= 2'b11;
                    valid <= 1'b1;
                end
                else if(req[3])
                begin
                    grant <= 2'b11;
                    pointer <= 2'b00;
                    valid <= 1'b1;
                end
            end



            2'b01:
            begin
                if(req[1])
                begin
                    grant <= 2'b01;
                    pointer <= 2'b10;
                    valid <= 1'b1;
                end
                else if(req[2])
                begin
                    grant <= 2'b10;
                    pointer <= 2'b11;
                    valid <= 1'b1;
                end
                else if(req[3])
                begin
                    grant <= 2'b11;
                    pointer <= 2'b00;
                    valid <= 1'b1;
                end
                else if(req[0])
                begin
                    grant <= 2'b00;
                    pointer <= 2'b01;
                    valid <= 1'b1;
                end
            end



            2'b10:
            begin
                if(req[2])
                begin
                    grant <= 2'b10;
                    pointer <= 2'b11;
                    valid <= 1'b1;
                end
                else if(req[3])
                begin
                    grant <= 2'b11;
                    pointer <= 2'b00;
                    valid <= 1'b1;
                end
                else if(req[0])
                begin
                    grant <= 2'b00;
                    pointer <= 2'b01;
                    valid <= 1'b1;
                end
                else if(req[1])
                begin
                    grant <= 2'b01;
                    pointer <= 2'b10;
                    valid <= 1'b1;
                end
            end



            2'b11:
            begin
                if(req[3])
                begin
                    grant <= 2'b11;
                    pointer <= 2'b00;
                    valid <= 1'b1;
                end
                else if(req[0])
                begin
                    grant <= 2'b00;
                    pointer <= 2'b01;
                    valid <= 1'b1;
                end
                else if(req[1])
                begin
                    grant <= 2'b01;
                    pointer <= 2'b10;
                    valid <= 1'b1;
                end
                else if(req[2])
                begin
                    grant <= 2'b10;
                    pointer <= 2'b11;
                    valid <= 1'b1;
                end
            end

            endcase

        end

    end

end

endmodule

Challenge10_ModeMux/mode_mux_tb.v
`timescale 1ns/1ps

module mode_mux_tb;


reg clk;
reg reset;
reg [3:0] req;
reg mode;

wire [1:0] grant;
wire valid;



mode_mux DUT(

    .clk(clk),
    .reset(reset),
    .req(req),
    .mode(mode),
    .grant(grant),
    .valid(valid)

);



always #5 clk = ~clk;



initial
begin

    $dumpfile("mode_mux.vcd");
    $dumpvars(0,mode_mux_tb);



    clk = 0;
    reset = 1;
    req = 4'b0000;
    mode = 0;



    #10;
    reset = 0;



    // -----------------------
    // Fixed Priority Testing
    // -----------------------

    mode = 0;


    req = 4'b0001;
    #10;


    req = 4'b0110;
    #10;


    req = 4'b1111;
    #10;



    // -----------------------
    // Round Robin Testing
    // -----------------------

    mode = 1;


    req = 4'b1111;
    #10;


    req = 4'b1111;
    #10;


    req = 4'b1111;
    #10;


    req = 4'b1111;
    #10;



    // Multiple requests

    req = 4'b1010;
    #10;


    req = 4'b0101;
    #10;



    $finish;

end



initial
begin

$monitor(
"Time=%0t | Mode=%b | Request=%b | Grant=%b | Valid=%b",
$time,
mode,
req,
grant,
valid
);

end


endmodule

Challenge10_ModeMux/mode_mux.vcd
$date
	Sun Jul 12 20:56:02 2026
$end
$version
	Icarus Verilog
$end
$timescale
	1ps
$end
$scope module mode_mux_tb $end
$var wire 1 ! valid $end
$var wire 2 " grant [1:0] $end
$var reg 1 # clk $end
$var reg 1 $ mode $end
$var reg 4 % req [3:0] $end
$var reg 1 & reset $end
$scope module DUT $end
$var wire 1 # clk $end
$var wire 1 $ mode $end
$var wire 4 ' req [3:0] $end
$var wire 1 & reset $end
$var reg 2 ( grant [1:0] $end
$var reg 2 ) pointer [1:0] $end
$var reg 1 ! valid $end
$upscope $end
$upscope $end
$enddefinitions $end
$comment Show the parameter values. $end
$dumpall
$end
#0
$dumpvars
b0 )
b0 (
b0 '
1&
b0 %
0$
0#
b0 "
0!
$end
#5000
1#
#10000
0#
b1 %
b1 '
0&
#15000
1!
1#
#20000
0#
b110 %
b110 '
#25000
b10 "
b10 (
1!
1#
#30000
0#
b1111 %
b1111 '
#35000
b11 "
b11 (
1!
1#
#40000
0#
1$
#45000
b1 )
b0 "
b0 (
1!
1#
#50000
0#
#55000
b10 )
b1 "
b1 (
1!
1#
#60000
0#
#65000
b11 )
b10 "
b10 (
1!
1#
#70000
0#
#75000
b0 )
b11 "
b11 (
1!
1#
#80000
0#
b1010 %
b1010 '
#85000
b10 )
b1 "
b1 (
1!
1#
#90000
0#
b101 %
b101 '
#95000
b11 )
b10 "
b10 (
1!
1#
