Challenge02_BitVault/bit_vault.v
module bit_vault(
    input clk,
    input we,
    input [1:0] addr,
    input [7:0] data_in,
    output [7:0] data_out
);

reg [7:0] reg_file [3:0];

// Write Operation
always @(posedge clk)
begin
    if (we)
        reg_file[addr] <= data_in;
end

// Read Operation
assign data_out = reg_file[addr];

endmodule

Challenge02_BitVault/bit_vault_tb.v
`timescale 1ns/1ps

module bit_vault_tb;

reg clk;
reg we;
reg [1:0] addr;
reg [7:0] data_in;

wire [7:0] data_out;

// Instantiate DUT
bit_vault uut(
    .clk(clk),
    .we(we),
    .addr(addr),
    .data_in(data_in),
    .data_out(data_out)
);

// Clock generation
always #5 clk = ~clk;

initial
begin

    $dumpfile("bit_vault.vcd");
    $dumpvars(0, bit_vault_tb);

    $monitor("Time=%0t WE=%b ADDR=%d DATA_IN=%d DATA_OUT=%d",
              $time,we,addr,data_in,data_out);

    clk = 0;
    we = 0;
    addr = 0;
    data_in = 0;

    // Write 10 to Register 0
    #10;
    we = 1;
    addr = 2'b00;
    data_in = 8'd10;

    #10;

    // Write 20 to Register 1
    addr = 2'b01;
    data_in = 8'd20;

    #10;

    // Write 30 to Register 2
    addr = 2'b10;
    data_in = 8'd30;

    #10;

    // Write 40 to Register 3
    addr = 2'b11;
    data_in = 8'd40;

    #10;

    // Disable Write
    we = 0;

    // Read Register 0
    addr = 2'b00;

    #10;

    // Read Register 1
    addr = 2'b01;

    #10;

    // Read Register 2
    addr = 2'b10;

    #10;

    // Read Register 3
    addr = 2'b11;

    #10;

    // Try overwrite while WE=0
    addr = 2'b01;
    data_in = 8'd99;

    #10;

    // Read Register 1 again
    addr = 2'b01;

    #20;

    $finish;

end

endmodule

Challenge02_BitVault/bit_vault.vcd
$date
	Sun Jul 12 19:54:46 2026
$end
$version
	Icarus Verilog
$end
$timescale
	1ps
$end
$scope module bit_vault_tb $end
$var wire 8 ! data_out [7:0] $end
$var reg 2 " addr [1:0] $end
$var reg 1 # clk $end
$var reg 8 $ data_in [7:0] $end
$var reg 1 % we $end
$scope module uut $end
$var wire 2 & addr [1:0] $end
$var wire 1 # clk $end
$var wire 8 ' data_in [7:0] $end
$var wire 8 ( data_out [7:0] $end
$var wire 1 % we $end
$upscope $end
$upscope $end
$enddefinitions $end
$comment Show the parameter values. $end
$dumpall
$end
#0
$dumpvars
bx (
b0 '
b0 &
0%
b0 $
0#
b0 "
bx !
$end
#5000
1#
#10000
0#
b1010 $
b1010 '
1%
#15000
b1010 !
b1010 (
1#
#20000
0#
b10100 $
b10100 '
bx !
bx (
b1 "
b1 &
#25000
b10100 !
b10100 (
1#
#30000
0#
b11110 $
b11110 '
bx !
bx (
b10 "
b10 &
#35000
b11110 !
b11110 (
1#
#40000
0#
b101000 $
b101000 '
bx !
bx (
b11 "
b11 &
#45000
b101000 !
b101000 (
1#
#50000
0#
b1010 !
b1010 (
b0 "
b0 &
0%
#55000
1#
#60000
0#
b10100 !
b10100 (
b1 "
b1 &
#65000
1#
#70000
0#
b11110 !
b11110 (
b10 "
b10 &
#75000
1#
#80000
0#
b101000 !
b101000 (
b11 "
b11 &
#85000
1#
#90000
0#
b1100011 $
b1100011 '
b10100 !
b10100 (
b1 "
b1 &
