Challenge03_ByteStreamer/byte_streamer.v
module byte_streamer(
    input clk,
    input reset,
    input shift_enable,
    input serial_in,
    output reg [7:0] parallel_out,
    output reg byte_ready
);

reg [2:0] bit_count;

always @(posedge clk or posedge reset)
begin
    if(reset)
    begin
        parallel_out <= 8'b00000000;
        bit_count <= 3'd0;
        byte_ready <= 1'b0;
    end

    else if(shift_enable)
    begin
        parallel_out <= {parallel_out[6:0], serial_in};

        if(bit_count == 3'd7)
        begin
            bit_count <= 3'd0;
            byte_ready <= 1'b1;
        end
        else
        begin
            bit_count <= bit_count + 1;
            byte_ready <= 1'b0;
        end
    end

    else
        byte_ready <= 1'b0;

end

endmodule

Challenge03_ByteStreamer/byte_streamer_tb.v
`timescale 1ns/1ps

module byte_streamer_tb;

reg clk;
reg reset;
reg shift_enable;
reg serial_in;

wire [7:0] parallel_out;
wire byte_ready;

byte_streamer uut(
    .clk(clk),
    .reset(reset),
    .shift_enable(shift_enable),
    .serial_in(serial_in),
    .parallel_out(parallel_out),
    .byte_ready(byte_ready)
);

// Clock generation
always #5 clk = ~clk;

initial
begin

    $dumpfile("byte_streamer.vcd");
    $dumpvars(0, byte_streamer_tb);

    $monitor("Time=%0t Reset=%b Shift=%b Serial=%b Parallel=%b Ready=%b",
             $time, reset, shift_enable, serial_in,
             parallel_out, byte_ready);

    clk = 0;
    reset = 1;
    shift_enable = 0;
    serial_in = 0;

    #10;
    reset = 0;
    shift_enable = 1;

    // Send 10101100

    serial_in = 1; #10;
    serial_in = 0; #10;
    serial_in = 1; #10;
    serial_in = 0; #10;
    serial_in = 1; #10;
    serial_in = 1; #10;
    serial_in = 0; #10;
    serial_in = 0; #10;

    shift_enable = 0;

    #20;

    $finish;

end

endmodule

Challenge03_ByteStreamer/byte_streamer.vcd
$date
	Sun Jul 12 20:00:05 2026
$end
$version
	Icarus Verilog
$end
$timescale
	1ps
$end
$scope module byte_streamer_tb $end
$var wire 8 ! parallel_out [7:0] $end
$var wire 1 " byte_ready $end
$var reg 1 # clk $end
$var reg 1 $ reset $end
$var reg 1 % serial_in $end
$var reg 1 & shift_enable $end
$scope module uut $end
$var wire 1 # clk $end
$var wire 1 $ reset $end
$var wire 1 % serial_in $end
$var wire 1 & shift_enable $end
$var reg 3 ' bit_count [2:0] $end
$var reg 1 " byte_ready $end
$var reg 8 ( parallel_out [7:0] $end
$upscope $end
$upscope $end
$enddefinitions $end
$comment Show the parameter values. $end
$dumpall
$end
#0
$dumpvars
b0 (
b0 '
0&
0%
1$
0#
0"
b0 !
$end
#5000
1#
#10000
0#
1%
1&
0$
#15000
b1 '
b1 !
b1 (
1#
#20000
0#
0%
#25000
b10 '
b10 !
b10 (
1#
#30000
0#
1%
#35000
b11 '
b101 !
b101 (
1#
#40000
0#
0%
#45000
b100 '
b1010 !
b1010 (
1#
#50000
0#
1%
#55000
b101 '
b10101 !
b10101 (
1#
#60000
0#
#65000
b110 '
b101011 !
b101011 (
1#
#70000
0#
0%
#75000
b111 '
b1010110 !
b1010110 (
1#
#80000
0#
#85000
1"
b0 '
b10101100 !
b10101100 (
1#
#90000
0#
0&
#95000
0"
1#
