Challenge08_DualClockFIFO/dual_clock_fifo.v
module dual_clock_fifo(
    input wr_clk,
    input rd_clk,
    input reset,

    input wr_en,
    input rd_en,

    input [7:0] data_in,
    output reg [7:0] data_out,

    output full,
    output empty
);

parameter DEPTH = 4;

reg [7:0] mem [0:DEPTH-1];

// Binary pointers
reg [2:0] wr_ptr_bin;
reg [2:0] rd_ptr_bin;

// Gray pointers
reg [2:0] wr_ptr_gray;
reg [2:0] rd_ptr_gray;

// Binary → Gray
function [2:0] bin2gray;
input [2:0] bin;
begin
    bin2gray = (bin >> 1) ^ bin;
end
endfunction

assign full =
    ((wr_ptr_bin + 1) % DEPTH) == (rd_ptr_bin % DEPTH);

assign empty =
    (wr_ptr_bin == rd_ptr_bin);

// Write Clock
always @(posedge wr_clk or posedge reset)
begin
    if(reset)
    begin
        wr_ptr_bin <= 0;
        wr_ptr_gray <= 0;
    end
    else if(wr_en && !full)
    begin
        mem[wr_ptr_bin[1:0]] <= data_in;
        wr_ptr_bin <= wr_ptr_bin + 1;
        wr_ptr_gray <= bin2gray(wr_ptr_bin + 1);
    end
end

// Read Clock
always @(posedge rd_clk or posedge reset)
begin
    if(reset)
    begin
        rd_ptr_bin <= 0;
        rd_ptr_gray <= 0;
        data_out <= 0;
    end
    else if(rd_en && !empty)
    begin
        data_out <= mem[rd_ptr_bin[1:0]];
        rd_ptr_bin <= rd_ptr_bin + 1;
        rd_ptr_gray <= bin2gray(rd_ptr_bin + 1);
    end
end

endmodule

Challenge08_DualClockFIFO/dual_clock_fifo_tb.v
`timescale 1ns/1ps

module dual_clock_fifo_tb;

reg wr_clk;
reg rd_clk;
reg reset;

reg wr_en;
reg rd_en;

reg [7:0] data_in;

wire [7:0] data_out;
wire full;
wire empty;

dual_clock_fifo uut(

.wr_clk(wr_clk),
.rd_clk(rd_clk),
.reset(reset),

.wr_en(wr_en),
.rd_en(rd_en),

.data_in(data_in),
.data_out(data_out),

.full(full),
.empty(empty)

);

// Different Clock Domains
always #5 wr_clk = ~wr_clk;
always #7 rd_clk = ~rd_clk;

initial
begin

$dumpfile("dual_clock_fifo.vcd");
$dumpvars(0,dual_clock_fifo_tb);

$monitor("Time=%0t WR=%b RD=%b DataIn=%d DataOut=%d Full=%b Empty=%b",
$time,wr_en,rd_en,data_in,data_out,full,empty);

wr_clk=0;
rd_clk=0;

reset=1;
wr_en=0;
rd_en=0;
data_in=0;

#20;
reset=0;

// Write
wr_en=1;

data_in=11;
#10;

data_in=22;
#10;

data_in=33;
#10;

data_in=44;
#10;

wr_en=0;

// Read
rd_en=1;

#60;

rd_en=0;

#20;

$finish;

end

endmodule

Challenge08_DualClockFIFO/dual_clock_fifo.vcd
$date
	Sun Jul 12 20:42:06 2026
$end
$version
	Icarus Verilog
$end
$timescale
	1ps
$end
$scope module dual_clock_fifo_tb $end
$var wire 1 ! full $end
$var wire 1 " empty $end
$var wire 8 # data_out [7:0] $end
$var reg 8 $ data_in [7:0] $end
$var reg 1 % rd_clk $end
$var reg 1 & rd_en $end
$var reg 1 ' reset $end
$var reg 1 ( wr_clk $end
$var reg 1 ) wr_en $end
$scope module uut $end
$var wire 8 * data_in [7:0] $end
$var wire 1 % rd_clk $end
$var wire 1 & rd_en $end
$var wire 1 ' reset $end
$var wire 1 ( wr_clk $end
$var wire 1 ) wr_en $end
$var wire 1 ! full $end
$var wire 1 " empty $end
$var parameter 32 + DEPTH $end
$var reg 8 , data_out [7:0] $end
$var reg 3 - rd_ptr_bin [2:0] $end
$var reg 3 . rd_ptr_gray [2:0] $end
$var reg 3 / wr_ptr_bin [2:0] $end
$var reg 3 0 wr_ptr_gray [2:0] $end
$scope function bin2gray $end
$var reg 3 1 bin [2:0] $end
$upscope $end
$upscope $end
$upscope $end
$enddefinitions $end
$comment Show the parameter values. $end
$dumpall
b100 +
$end
#0
$dumpvars
bx 1
b0 0
b0 /
b0 .
b0 -
b0 ,
b0 *
0)
0(
1'
0&
0%
b0 $
b0 #
1"
0!
$end
#5000
1(
#7000
1%
#10000
0(
#14000
0%
#15000
1(
#20000
0(
b1011 $
b1011 *
1)
0'
#21000
1%
#25000
b1 0
0"
b1 /
b1 1
1(
#28000
0%
#30000
0(
b10110 $
b10110 *
#35000
b11 0
b10 /
b10 1
1(
1%
#40000
0(
b100001 $
b100001 *
#42000
0%
#45000
b10 0
1!
b11 /
b11 1
1(
#49000
1%
#50000
0(
b101100 $
b101100 *
#55000
1(
#56000
0%
#60000
0(
1&
0)
#63000
b1 .
0!
b1 -
b1011 #
b1011 ,
b1 1
1%
#65000
1(
#70000
0(
0%
#75000
1(
#77000
b11 .
b10 -
b10110 #
b10110 ,
b10 1
1%
#80000
0(
#84000
0%
#85000
1(
#90000
0(
#91000
b10 .
1"
b11 -
b100001 #
b100001 ,
b11 1
1%
#95000
1(
#98000
0%
#100000
0(
#105000
1(
1%
#110000
0(
#112000
0%
#115000
1(
#119000
1%
#120000
0(
0&
