Challenge09_PulseStretch/pulse_stretch.v
module pulse_stretch(
    input clk,
    input reset,
    input pulse_in,
    output reg pulse_out
);

reg [2:0] counter;
reg active;

always @(posedge clk or posedge reset)
begin
    if(reset)
    begin
        pulse_out <= 0;
        counter <= 0;
        active <= 0;
    end
    else
    begin
        if(!active)
        begin
            if(pulse_in)
            begin
                active <= 1;
                pulse_out <= 1;
                counter <= 3'd5;
            end
            else
            begin
                pulse_out <= 0;
            end
        end
        else
        begin
            if(counter > 1)
            begin
                counter <= counter - 1;
                pulse_out <= 1;
            end
            else
            begin
                counter <= 0;
                pulse_out <= 0;
                active <= 0;
            end
        end
    end
end

endmodule

Challenge09_PulseStretch/pulse_stretch_tb.v
`timescale 1ns/1ps

module pulse_stretch_tb;

reg clk;
reg reset;
reg pulse_in;

wire pulse_out;

pulse_stretch uut(
    .clk(clk),
    .reset(reset),
    .pulse_in(pulse_in),
    .pulse_out(pulse_out)
);

always #5 clk = ~clk;

initial
begin

    $dumpfile("pulse_stretch.vcd");
    $dumpvars(0,pulse_stretch_tb);

    $monitor("Time=%0t PulseIn=%b PulseOut=%b",
             $time,pulse_in,pulse_out);

    clk = 0;
    reset = 1;
    pulse_in = 0;

    #10;
    reset = 0;

    // First pulse
    #10;
    pulse_in = 1;
    #10;
    pulse_in = 0;

    // Ignored pulse during stretch
    #20;
    pulse_in = 1;
    #10;
    pulse_in = 0;

    // New pulse after stretch
    #60;
    pulse_in = 1;
    #10;
    pulse_in = 0;

    #80;

    $finish;

end

endmodule

Challenge09_PulseStretch/pulse_stretch.vcd
$date
	Sun Jul 12 20:48:15 2026
$end
$version
	Icarus Verilog
$end
$timescale
	1ps
$end
$scope module pulse_stretch_tb $end
$var wire 1 ! pulse_out $end
$var reg 1 " clk $end
$var reg 1 # pulse_in $end
$var reg 1 $ reset $end
$scope module uut $end
$var wire 1 " clk $end
$var wire 1 # pulse_in $end
$var wire 1 $ reset $end
$var reg 1 % active $end
$var reg 3 & counter [2:0] $end
$var reg 1 ! pulse_out $end
$upscope $end
$upscope $end
$enddefinitions $end
$comment Show the parameter values. $end
$dumpall
$end
#0
$dumpvars
b0 &
0%
1$
0#
0"
0!
$end
#5000
1"
#10000
0"
0$
#15000
1"
#20000
0"
1#
#25000
b101 &
1!
1%
1"
#30000
0"
0#
#35000
b100 &
1"
#40000
0"
#45000
b11 &
1"
#50000
0"
1#
#55000
b10 &
1"
#60000
0"
0#
#65000
b1 &
1"
#70000
0"
#75000
0%
0!
b0 &
1"
#80000
0"
#85000
1"
#90000
0"
#95000
1"
#100000
0"
#105000
1"
#110000
0"
#115000
1"
#120000
0"
1#
#125000
b101 &
1!
1%
1"
#130000
0"
0#
#135000
b100 &
1"
#140000
0"
#145000
b11 &
1"
#150000
0"
#155000
b10 &
1"
#160000
0"
#165000
b1 &
1"
#170000
0"
#175000
0%
0!
b0 &
1"
